cvutil/__init__.py
cvutil/envs.py
cvutil/ffmpeg.py
cvutil/image.py
cvutil/logger.py
cvutil/math.py
cvutil/path.py
cvutil/random.py
cvutil/strings.py
cvutil/train.py
cvutil-0.0.9.dist-info/licenses/LICENSE
cvutil-0.0.9.dist-info/METADATA
cvutil-0.0.9.dist-info/WHEEL
cvutil-0.0.9.dist-info/top_level.txt
cvutil-0.0.9.dist-info/RECORD
